fastnda/__init__.py
fastnda/btsda.py
fastnda/cli.py
fastnda/dicts.py
fastnda/main.py
fastnda/nda.py
fastnda/ndax.py
fastnda/utils.py
fastnda/version.py
fastnda-1.0.1.dist-info/entry_points.txt
fastnda-1.0.1.dist-info/licenses/LICENSE
fastnda-1.0.1.dist-info/WHEEL
fastnda-1.0.1.dist-info/METADATA
fastnda-1.0.1.dist-info/RECORD
