Metadata-Version: 2.4
Name: fastnda
Version: 1.0.1
Summary: Read Neware nda and ndax files fast.
Requires-Python: >=3.10
License-Expression: BSD-3-Clause
Classifier: Development Status :: 5 - Production/Stable
Classifier: Programming Language :: Python :: 3
Classifier: Programming Language :: Python :: 3.10
Classifier: Programming Language :: Python :: 3.11
Classifier: Programming Language :: Python :: 3.12
Classifier: Programming Language :: Python :: 3.13
Classifier: Operating System :: OS Independent
License-File: LICENSE
Requires-Dist: defusedxml>=0.7.1
Requires-Dist: numpy>=2.2.6
Requires-Dist: polars>=1.33.1
Requires-Dist: tqdm>=4.67.1
Requires-Dist: typer>=0.20.0
Requires-Dist: xmltodict>=1.0.2
Requires-Dist: bumpver>=2025.1131 ; extra == "dev"
Requires-Dist: pre-commit>=4.2.0 ; extra == "dev"
Requires-Dist: pandas>=2.3.1 ; extra == "dev"
Requires-Dist: pyarrow>=23.0.0 ; extra == "dev"
Requires-Dist: pytest>=8.4.1 ; extra == "dev"
Requires-Dist: ruff>=0.12.8 ; extra == "dev"
Requires-Dist: tables>=3.10.1 ; extra == "dev"
Requires-Dist: pandas>=2.3.1 ; extra == "extras"
Requires-Dist: pyarrow>=23.0.0 ; extra == "extras"
Requires-Dist: tables>=3.10.1 ; extra == "extras"
Provides-Extra: dev
Provides-Extra: extras
